[
  {
    "name": "司法院－刑事補償",
    "code": "TPC",
    "divisions": [
      {
        "name": "刑事",
        "code": "M"
      }
    ]
  }, {
    "name": "司法院－訴願決定",
    "code": "TPU",
    "divisions": [
      {
        "name": "行政",
        "code": "A"
      }
    ]
  }, {
    "name": "司法院職務法庭",
    "code": "TPJ",
    "divisions": [
      {
        "name": "公懲",
        "code": "P"
      }
    ]
  }, {
    "name": "最高法院",
    "code": "TPS",
    "divisions": [
      {
        "name": "刑事",
        "code": "M"
      }, {
        "name": "民事",
        "code": "V"
      }
    ]
  }, {
    "name": "最高行政法院",
    "code": "TPA",
    "divisions": [
      {
        "name": "行政",
        "code": "A"
      }
    ]
  }, {
    "name": "公務員懲戒委員會",
    "code": "TPP",
    "divisions": [
      {
        "name": "公懲",
        "code": "P"
      }
    ]
  }, {
    "name": "臺灣高等法院",
    "code": "TPH",
    "divisions": [
      {
        "name": "刑事",
        "code": "M"
      }, {
        "name": "民事",
        "code": "V"
      }
    ]
  }, {
    "name": "臺灣高等法院－訴願決定",
    "code": "TPH",
    "divisions": [
      {
        "name": "行政",
        "code": "A"
      }
    ]
  }, {
    "name": "臺北高等行政法院",
    "code": "TPB",
    "divisions": [
      {
        "name": "行政",
        "code": "A"
      }
    ]
  }, {
    "name": "臺中高等行政法院",
    "code": "TCB",
    "divisions": [
      {
        "name": "行政",
        "code": "A"
      }
    ]
  }, {
    "name": "高雄高等行政法院",
    "code": "KSB",
    "divisions": [
      {
        "name": "行政",
        "code": "A"
      }
    ]
  }, {
    "name": "智慧財產法院",
    "code": "IPC",
    "divisions": [
      {
        "name": "刑事",
        "code": "M"
      }, {
        "name": "民事",
        "code": "V"
      }, {
        "name": "行政",
        "code": "A"
      }
    ]
  }, {
    "name": "臺灣高等法院 臺中分院",
    "code": "TCH",
    "divisions": [
      {
        "name": "刑事",
        "code": "M"
      }, {
        "name": "民事",
        "code": "V"
      }
    ]
  }, {
    "name": "臺灣高等法院 臺南分院",
    "code": "TNH",
    "divisions": [
      {
        "name": "刑事",
        "code": "M"
      }, {
        "name": "民事",
        "code": "V"
      }
    ]
  }, {
    "name": "臺灣高等法院 高雄分院",
    "code": "KSH",
    "divisions": [
      {
        "name": "刑事",
        "code": "M"
      }, {
        "name": "民事",
        "code": "V"
      }
    ]
  }, {
    "name": "臺灣高等法院 花蓮分院",
    "code": "HLH",
    "divisions": [
      {
        "name": "刑事",
        "code": "M"
      }, {
        "name": "民事",
        "code": "V"
      }
    ]
  }, {
    "name": "臺灣臺北地方法院",
    "code": "TPD",
    "divisions": [
      {
        "name": "刑事",
        "code": "M"
      }, {
        "name": "民事",
        "code": "V"
      }, {
        "name": "行政",
        "code": "A"
      }
    ]
  }, {
    "name": "臺灣士林地方法院",
    "code": "SLD",
    "divisions": [
      {
        "name": "刑事",
        "code": "M"
      }, {
        "name": "民事",
        "code": "V"
      }, {
        "name": "行政",
        "code": "A"
      }
    ]
  }, {
    "name": "臺灣新北地方法院",
    "code": "PCD",
    "divisions": [
      {
        "name": "刑事",
        "code": "M"
      }, {
        "name": "民事",
        "code": "V"
      }, {
        "name": "行政",
        "code": "A"
      }
    ]
  }, {
    "name": "臺灣宜蘭地方法院",
    "code": "ILD",
    "divisions": [
      {
        "name": "刑事",
        "code": "M"
      }, {
        "name": "民事",
        "code": "V"
      }, {
        "name": "行政",
        "code": "A"
      }
    ]
  }, {
    "name": "臺灣基隆地方法院",
    "code": "KLD",
    "divisions": [
      {
        "name": "刑事",
        "code": "M"
      }, {
        "name": "民事",
        "code": "V"
      }, {
        "name": "行政",
        "code": "A"
      }
    ]
  }, {
    "name": "臺灣桃園地方法院",
    "code": "TYD",
    "divisions": [
      {
        "name": "刑事",
        "code": "M"
      }, {
        "name": "民事",
        "code": "V"
      }, {
        "name": "行政",
        "code": "A"
      }
    ]
  }, {
    "name": "臺灣新竹地方法院",
    "code": "SCD",
    "divisions": [
      {
        "name": "刑事",
        "code": "M"
      }, {
        "name": "民事",
        "code": "V"
      }, {
        "name": "行政",
        "code": "A"
      }
    ]
  }, {
    "name": "臺灣苗栗地方法院",
    "code": "MLD",
    "divisions": [
      {
        "name": "刑事",
        "code": "M"
      }, {
        "name": "民事",
        "code": "V"
      }, {
        "name": "行政",
        "code": "A"
      }
    ]
  }, {
    "name": "臺灣臺中地方法院",
    "code": "TCD",
    "divisions": [
      {
        "name": "刑事",
        "code": "M"
      }, {
        "name": "民事",
        "code": "V"
      }, {
        "name": "行政",
        "code": "A"
      }
    ]
  }, {
    "name": "臺灣彰化地方法院",
    "code": "CHD",
    "divisions": [
      {
        "name": "刑事",
        "code": "M"
      }, {
        "name": "民事",
        "code": "V"
      }, {
        "name": "行政",
        "code": "A"
      }
    ]
  }, {
    "name": "臺灣南投地方法院",
    "code": "TND",
    "divisions": [
      {
        "name": "刑事",
        "code": "M"
      }, {
        "name": "民事",
        "code": "V"
      }, {
        "name": "行政",
        "code": "A"
      }
    ]
  }, {
    "name": "臺灣雲林地方法院",
    "code": "ULD",
    "divisions": [
      {
        "name": "刑事",
        "code": "M"
      }, {
        "name": "民事",
        "code": "V"
      }, {
        "name": "行政",
        "code": "A"
      }
    ]
  }, {
    "name": "臺灣嘉義地方法院",
    "code": "CYD",
    "divisions": [
      {
        "name": "刑事",
        "code": "M"
      }, {
        "name": "民事",
        "code": "V"
      }, {
        "name": "行政",
        "code": "A"
      }
    ]
  }, {
    "name": "臺灣臺南地方法院",
    "code": "TND",
    "divisions": [
      {
        "name": "刑事",
        "code": "M"
      }, {
        "name": "民事",
        "code": "V"
      }, {
        "name": "行政",
        "code": "A"
      }
    ]
  }, {
    "name": "臺灣高雄地方法院",
    "code": "KSD",
    "divisions": [
      {
        "name": "刑事",
        "code": "M"
      }, {
        "name": "民事",
        "code": "V"
      }, {
        "name": "行政",
        "code": "A"
      }
    ]
  }, {
    "name": "臺灣花蓮地方法院",
    "code": "HLD",
    "divisions": [
      {
        "name": "刑事",
        "code": "M"
      }, {
        "name": "民事",
        "code": "V"
      }, {
        "name": "行政",
        "code": "A"
      }
    ]
  }, {
    "name": "臺灣臺東地方法院",
    "code": "TTD",
    "divisions": [
      {
        "name": "刑事",
        "code": "M"
      }, {
        "name": "民事",
        "code": "V"
      }, {
        "name": "行政",
        "code": "A"
      }
    ]
  }, {
    "name": "臺灣屏東地方法院",
    "code": "PTD",
    "divisions": [
      {
        "name": "刑事",
        "code": "M"
      }, {
        "name": "民事",
        "code": "V"
      }, {
        "name": "行政",
        "code": "A"
      }
    ]
  }, {
    "name": "臺灣澎湖地方法院",
    "code": "PHD",
    "divisions": [
      {
        "name": "刑事",
        "code": "M"
      }, {
        "name": "民事",
        "code": "V"
      }, {
        "name": "行政",
        "code": "A"
      }
    ]
  }, {
    "name": "福建高等法院金門分院",
    "code": "KMH",
    "divisions": [
      {
        "name": "刑事",
        "code": "M"
      }, {
        "name": "民事",
        "code": "V"
      }
    ]
  }, {
    "name": "福建金門地方法院",
    "code": "KMD",
    "divisions": [
      {
        "name": "刑事",
        "code": "M"
      }, {
        "name": "民事",
        "code": "V"
      }, {
        "name": "行政",
        "code": "A"
      }
    ]
  }, {
    "name": "福建連江地方法院",
    "code": "LCD",
    "divisions": [
      {
        "name": "刑事",
        "code": "M"
      }, {
        "name": "民事",
        "code": "V"
      }, {
        "name": "行政",
        "code": "A"
      }
    ]
  }, {
    "name": "臺灣高雄少年及家事法院",
    "code": "KSY",
    "divisions": [
      {
        "name": "民事",
        "code": "V"
      }
    ]
  }
]

